nemapi/URLs.py
nemapi/__init__.py
nemapi-1.0.6.dist-info/LICENSE
nemapi-1.0.6.dist-info/METADATA
nemapi-1.0.6.dist-info/WHEEL
nemapi-1.0.6.dist-info/top_level.txt
nemapi-1.0.6.dist-info/RECORD
