Metadata-Version: 2.1
Name: nemapi
Version: 1.0.6
Summary: Access to public National Electricity Market data through nemmarket API.
Home-page: UNKNOWN
Author: Jonathon Emerick
Author-email: jonathon.emerick@uq.net.au
License: MIT
Platform: UNKNOWN
Classifier: License :: OSI Approved :: MIT License
Classifier: Programming Language :: Python :: 3
Classifier: Programming Language :: Python :: 3.7
Requires-Dist: datetime
Requires-Dist: requests
Requires-Dist: pandas
